mooq/__init__.py
mooq/__version__.py
mooq/base.py
mooq/connect.py
mooq/in_memory.py
mooq/rabbit.py
mooq-0.1.1.dist-info/DESCRIPTION.rst
mooq-0.1.1.dist-info/METADATA
mooq-0.1.1.dist-info/RECORD
mooq-0.1.1.dist-info/WHEEL
mooq-0.1.1.dist-info/metadata.json
mooq-0.1.1.dist-info/top_level.txt
