Metadata-Version: 2.0
Name: mooq
Version: 0.1.1
Summary: An asyncio compatible library for interacting with a RabbitMQ AMQP broker
Home-page: https://github.com/jeremyarr/mooq
Author: Jeremy Arr
Author-email: jeremyarr@gmail.com
License: MIT
Keywords: amqp,pika,rabbitmq
Platform: UNKNOWN
Classifier: Development Status :: 2 - Pre-Alpha
Classifier: License :: OSI Approved :: MIT License
Classifier: Intended Audience :: Developers
Classifier: Programming Language :: Python :: 3.6
Classifier: Topic :: Communications
Requires-Dist: pika
